curlyboi/__init__.py
curlyboi/__version__.py
curlyboi/_curlyboi.cpython-37m-darwin.so
curlyboi/cli.py
curlyboi-0.3.0.dist-info/LICENSE
curlyboi-0.3.0.dist-info/METADATA
curlyboi-0.3.0.dist-info/WHEEL
curlyboi-0.3.0.dist-info/entry_points.txt
curlyboi-0.3.0.dist-info/top_level.txt
curlyboi-0.3.0.dist-info/RECORD
