Metadata-Version: 2.1
Name: curlyboi
Version: 0.3.0
Summary: A simple curlyboi game written in C using ncurses.
Home-page: https://github.com/vinayak-mehta/curlyboi
Maintainer: Vinayak Mehta
Maintainer-email: vmehta94@gmail.com
License: MIT
Platform: UNKNOWN
Classifier: License :: OSI Approved :: MIT License
Classifier: Programming Language :: Python :: 3.6
Classifier: Programming Language :: Python :: 3.7
Classifier: Programming Language :: Python :: 3.8
Classifier: Programming Language :: Python :: 3.9
Requires-Dist: Click (>=7.0)
Provides-Extra: dev
Requires-Dist: Sphinx (>=2.2.1) ; extra == 'dev'
Requires-Dist: Click (>=7.0) ; extra == 'dev'
